CHANGELOG
License.txt
MANIFEST.in
README.rst
VERSION
setup.py
documentation/Makefile
documentation/class.rst
documentation/common.rst
documentation/conf.py
documentation/creating.rst
documentation/extending.rst
documentation/index.rst
documentation/tuning.rst
examples/single-note-example.py
src/MIDIUtil.egg-info/PKG-INFO
src/MIDIUtil.egg-info/SOURCES.txt
src/MIDIUtil.egg-info/dependency_links.txt
src/MIDIUtil.egg-info/top_level.txt
src/midiutil/MidiFile.py
src/midiutil/__init__.py
src/unittests/miditest.py